nonebot_plugin_novelai/__init__.py
nonebot_plugin_novelai/aidraw.py
nonebot_plugin_novelai/amusement/ramdomgirl.py
nonebot_plugin_novelai/amusement/wordbank.py
nonebot_plugin_novelai/backend/__init__.py
nonebot_plugin_novelai/backend/base.py
nonebot_plugin_novelai/backend/naifu.py
nonebot_plugin_novelai/backend/novelai.py
nonebot_plugin_novelai/backend/sd.py
nonebot_plugin_novelai/config.py
nonebot_plugin_novelai/extension/anlas.py
nonebot_plugin_novelai/extension/daylimit.py
nonebot_plugin_novelai/extension/deepdanbooru.py
nonebot_plugin_novelai/extension/translation.py
nonebot_plugin_novelai/fifo.py
nonebot_plugin_novelai/locales/__init__.py
nonebot_plugin_novelai/locales/en.py
nonebot_plugin_novelai/locales/jp.py
nonebot_plugin_novelai/locales/moe_jp.py
nonebot_plugin_novelai/locales/moe_zh.py
nonebot_plugin_novelai/locales/zh.py
nonebot_plugin_novelai/manage.py
nonebot_plugin_novelai/outofdate/explicit_api.py
nonebot_plugin_novelai/utils/__init__.py
nonebot_plugin_novelai/utils/data.py
nonebot_plugin_novelai/utils/prepocess.py
nonebot_plugin_novelai/utils/save.py
nonebot_plugin_novelai/version.py
nonebot_plugin_novelai-0.5.9.dist-info/WHEEL
nonebot_plugin_novelai-0.5.9.dist-info/METADATA
nonebot_plugin_novelai-0.5.9.dist-info/licenses/LICENSE
nonebot_plugin_novelai-0.5.9.dist-info/RECORD
