Metadata-Version: 2.1
Name: nonebot-plugin-novelai
Version: 0.5.9
Summary: 基于nonebot2的novelai绘图插件
License: MIT
Author-email: Sena <34237511+sena-nana@users.noreply.github.com>
Requires-Python: >=3.8
Requires-Dist: aiofiles>=22.1.0
Requires-Dist: aiohttp>=3.8.3
Requires-Dist: githubkit>=0.9.4
Requires-Dist: lxml>=4.9.2
Requires-Dist: mistune>=2.0.4
Requires-Dist: nonebot-adapter-onebot>=2.1.3
Requires-Dist: nonebot2>=2.0.0b4
Requires-Dist: pillow>=9.2.0
Requires-Dist: xmltodict>=0.13.0
